easy_px4_utils/__init__.py
easy_px4_utils/directory.py
easy_px4_utils/info.py
easy_px4_utils-0.1.5.dist-info/METADATA
easy_px4_utils-0.1.5.dist-info/WHEEL
easy_px4_utils-0.1.5.dist-info/top_level.txt
easy_px4_utils-0.1.5.dist-info/RECORD
